Workbook
Name Weeks: Inputs!$B$2
Name PayrollTax: Inputs!$B$3
Name Liability: Inputs!$B$4
Name Benefits: Inputs!$B$5
Name Kit: Inputs!$B$6
Name LeaveDays: Inputs!$B$7
Name Holidays: Inputs!$B$8
Name SickDays: Inputs!$B$9

Sheet Inputs
A1: What it is | B1: Your number
A2: Weeks per year | B2: 52
A3: Employer payroll tax | B3: 0.0765
A4: Liability and cover | B4: 0.035
A5: Benefits per person / year | B5: 4800
A6: Equipment and phone / year | B6: 2400
A7: Paid leave days | B7: 10
A8: Public holidays | B8: 6
A9: Sick days allowed | B9: 4
A11: Every one of these is yours to set. Rates differ by country, state and trade.

Sheet Staff
A1: Name | B1: Role | C1: Hourly rate | D1: Hours / week | E1: Charge-out rate
A2: Ana Ruiz | B2: Fitter | C2: 22 | D2: 40 | E2: 45
A3: Ben Cole | B3: Apprentice | C3: 16.5 | D3: 40 | E3: 32
A4: Chris Day | B4: Lead fitter | C4: 28 | D4: 40 | E4: 58
A5: Dina Petrou | B5: Office | C5: 19 | D5: 30 | E5: 0

Sheet Cost
A1: Name | B1: Paid hours | C1: Wage | D1: On-costs | E1: Total cost | F1: Cost / paid hour | G1: Hours worked | H1: Cost / hour worked | I1: Charge-out | J1: Margin you think | K1: Margin you get
A2: =Staff!A2 | B2: =Staff!D2*Weeks | C2: =Staff!C2*B2 | D2: =C2*PayrollTax+C2*Liability+Benefits+Kit | E2: =C2+D2 | F2: =E2/B2 | G2: =B2-(LeaveDays+Holidays+SickDays)*(Staff!D2/5) | H2: =E2/G2 | I2: =Staff!E2 | J2: =IF(I2=0,"",(I2-Staff!C2)/I2) | K2: =IF(I2=0,"",(I2-H2)/I2)
A3: =Staff!A3 | B3: =Staff!D3*Weeks | C3: =Staff!C3*B3 | D3: =C3*PayrollTax+C3*Liability+Benefits+Kit | E3: =C3+D3 | F3: =E3/B3 | G3: =B3-(LeaveDays+Holidays+SickDays)*(Staff!D3/5) | H3: =E3/G3 | I3: =Staff!E3 | J3: =IF(I3=0,"",(I3-Staff!C3)/I3) | K3: =IF(I3=0,"",(I3-H3)/I3)
A4: =Staff!A4 | B4: =Staff!D4*Weeks | C4: =Staff!C4*B4 | D4: =C4*PayrollTax+C4*Liability+Benefits+Kit | E4: =C4+D4 | F4: =E4/B4 | G4: =B4-(LeaveDays+Holidays+SickDays)*(Staff!D4/5) | H4: =E4/G4 | I4: =Staff!E4 | J4: =IF(I4=0,"",(I4-Staff!C4)/I4) | K4: =IF(I4=0,"",(I4-H4)/I4)
A5: =Staff!A5 | B5: =Staff!D5*Weeks | C5: =Staff!C5*B5 | D5: =C5*PayrollTax+C5*Liability+Benefits+Kit | E5: =C5+D5 | F5: =E5/B5 | G5: =B5-(LeaveDays+Holidays+SickDays)*(Staff!D5/5) | H5: =E5/G5 | I5: =Staff!E5 | J5: =IF(I5=0,"",(I5-Staff!C5)/I5) | K5: =IF(I5=0,"",(I5-H5)/I5)
A6: TOTAL | C6: =SUM(C2:C5) | D6: =SUM(D2:D5) | E6: =SUM(E2:E5)
A8: Uplift on the wage, per hour worked | B8: =H2/Staff!C2-1
