Workbook

Sheet Categories
A1: Category | B1: Monthly budget
A2: Fuel | B2: 900
A3: Materials | B3: 1200
A4: Tools | B4: 400
A5: Van service | B5: 300
A6: Insurance | B6: 250
A7: Phone | B7: 80
A8: Subscriptions | B8: 60
A9: Parking | B9: 120

Sheet Expenses
A1: Date | B1: Supplier | C1: Category | D1: Amount | E1: Method | F1: Business percent | G1: Claimable | H1: Known
A2: 46266 | B2: Shell Riverside | C2: Fuel | D2: 116.4 | E2: Card | F2: 1 | G2: =D2*F2 | H2: =IF(COUNTIF(Categories!$A$2:$A$9,$C2)=0,"CHECK","ok")
A3: 46266 | B3: Home Depot | C3: Materials | D3: 158.6 | E3: Card | F3: 1 | G3: =D3*F3 | H3: =IF(COUNTIF(Categories!$A$2:$A$9,$C3)=0,"CHECK","ok")
A4: 46267 | B4: LAZ Parking | C4: Parking | D4: 9.5 | E4: Cash | F4: 1 | G4: =D4*F4 | H4: =IF(COUNTIF(Categories!$A$2:$A$9,$C4)=0,"CHECK","ok")
A5: 46267 | B5: Exxon Midtown | C5: Fuel | D5: 120.25 | E5: Card | F5: 1 | G5: =D5*F5 | H5: =IF(COUNTIF(Categories!$A$2:$A$9,$C5)=0,"CHECK","ok")
A6: 46268 | B6: Harbor Freight | C6: Tools | D6: 129.99 | E6: Card | F6: 1 | G6: =D6*F6 | H6: =IF(COUNTIF(Categories!$A$2:$A$9,$C6)=0,"CHECK","ok")
A7: 46269 | B7: Shell Riverside | C7: Fuel | D7: 113.1 | E7: Card | F7: 1 | G7: =D7*F7 | H7: =IF(COUNTIF(Categories!$A$2:$A$9,$C7)=0,"CHECK","ok")
A8: 46269 | B8: Verizon | C8: Phone | D8: 42 | E8: DD | F8: 0.6 | G8: =D8*F8 | H8: =IF(COUNTIF(Categories!$A$2:$A$9,$C8)=0,"CHECK","ok")
A9: 46270 | B9: Home Depot | C9: Materials | D9: 124.2 | E9: Card | F9: 1 | G9: =D9*F9 | H9: =IF(COUNTIF(Categories!$A$2:$A$9,$C9)=0,"CHECK","ok")
A10: 46272 | B10: Chevron North | C10: Fuel | D10: 125.75 | E10: Card | F10: 1 | G10: =D10*F10 | H10: =IF(COUNTIF(Categories!$A$2:$A$9,$C10)=0,"CHECK","ok")
A11: 46272 | B11: Adobe | C11: Subscriptions | D11: 19.99 | E11: DD | F11: 1 | G11: =D11*F11 | H11: =IF(COUNTIF(Categories!$A$2:$A$9,$C11)=0,"CHECK","ok")
A12: 46273 | B12: Downtown Garage | C12: Parking | D12: 6 | E12: Cash | F12: 1 | G12: =D12*F12 | H12: =IF(COUNTIF(Categories!$A$2:$A$9,$C12)=0,"CHECK","ok")
A13: 46273 | B13: Ace Hardware | C13: Tools | D13: 64.5 | E13: Card | F13: 1 | G13: =D13*F13 | H13: =IF(COUNTIF(Categories!$A$2:$A$9,$C13)=0,"CHECK","ok")
... A42: 46295 | B42: Home office share | C42: Phone | D42: 28 | E42: DD | F42: 0.5 | G42: =D42*F42 | H42: =IF(COUNTIF(Categories!$A$2:$A$9,$C42)=0,"CHECK","ok")

Sheet Summary
A1: Category | B1: Spend | C1: Claimable | D1: Share of spend | E1: Budget | F1: Over / under
A2: =Categories!A2 | B2: =SUMIF(Expenses!$C$2:$C$42,$A2,Expenses!$D$2:$D$42) | C2: =SUMIF(Expenses!$C$2:$C$42,$A2,Expenses!$G$2:$G$42) | D2: =B2/$B$10 | E2: =Categories!B2 | F2: =B2-E2
A3: =Categories!A3 | B3: =SUMIF(Expenses!$C$2:$C$42,$A3,Expenses!$D$2:$D$42) | C3: =SUMIF(Expenses!$C$2:$C$42,$A3,Expenses!$G$2:$G$42) | D3: =B3/$B$10 | E3: =Categories!B3 | F3: =B3-E3
A4: =Categories!A4 | B4: =SUMIF(Expenses!$C$2:$C$42,$A4,Expenses!$D$2:$D$42) | C4: =SUMIF(Expenses!$C$2:$C$42,$A4,Expenses!$G$2:$G$42) | D4: =B4/$B$10 | E4: =Categories!B4 | F4: =B4-E4
A5: =Categories!A5 | B5: =SUMIF(Expenses!$C$2:$C$42,$A5,Expenses!$D$2:$D$42) | C5: =SUMIF(Expenses!$C$2:$C$42,$A5,Expenses!$G$2:$G$42) | D5: =B5/$B$10 | E5: =Categories!B5 | F5: =B5-E5
A6: =Categories!A6 | B6: =SUMIF(Expenses!$C$2:$C$42,$A6,Expenses!$D$2:$D$42) | C6: =SUMIF(Expenses!$C$2:$C$42,$A6,Expenses!$G$2:$G$42) | D6: =B6/$B$10 | E6: =Categories!B6 | F6: =B6-E6
A7: =Categories!A7 | B7: =SUMIF(Expenses!$C$2:$C$42,$A7,Expenses!$D$2:$D$42) | C7: =SUMIF(Expenses!$C$2:$C$42,$A7,Expenses!$G$2:$G$42) | D7: =B7/$B$10 | E7: =Categories!B7 | F7: =B7-E7
A8: =Categories!A8 | B8: =SUMIF(Expenses!$C$2:$C$42,$A8,Expenses!$D$2:$D$42) | C8: =SUMIF(Expenses!$C$2:$C$42,$A8,Expenses!$G$2:$G$42) | D8: =B8/$B$10 | E8: =Categories!B8 | F8: =B8-E8
A9: =Categories!A9 | B9: =SUMIF(Expenses!$C$2:$C$42,$A9,Expenses!$D$2:$D$42) | C9: =SUMIF(Expenses!$C$2:$C$42,$A9,Expenses!$G$2:$G$42) | D9: =B9/$B$10 | E9: =Categories!B9 | F9: =B9-E9
A10: TOTAL | B10: =SUM(B2:B9) | C10: =SUM(C2:C9) | E10: =SUM(E2:E9) | F10: =SUM(F2:F9)
A12: Rows to check | B12: =COUNTIF(Expenses!$H$2:$H$42,"CHECK")
A13: Spend in no category | B13: =SUM(Expenses!$D$2:$D$42)-$B$10
